Workbook

Sheet A.1 Costos
A1: Tabla A.1 — Resumen de costos del proyecto
A2: Equipo de 7 integrantes (1 Jefe de Proyecto + 6 Programadores) · Período: 12 meses
A4: Concepto | B4: Detalle | C4: Monto mensual | D4: Monto anual
A5: Jefe de Proyecto | B5: Sueldo mensual $1.200.000 | C5: 1200000 | D5: =C5*12 -> 14400000
A6: Programadores | B6: Sueldo mensual $900.000 c/u (6 personas) | C6: =900000*6 -> 5400000 | D6: =C6*12 -> 64800000
A7: Total RRHH | B7: Suma de sueldos | C7: =C5+C6 -> 6600000 | D7: =C7*12 -> 79200000
A8: Indirectos | B8: Arriendo, servicios, materiales, imprevistos (15% RRHH) | C8: =ROUND(C7*0.15,0) -> 990000 | D8: =C8*12 -> 11880000
A9: Total mensual con indirectos | B9: RRHH + Indirectos | C9: =C7+C8 -> 7590000 | D9: =C9*12 -> 91080000
A10: Caja / Contingencia | B10: 10% del total anual con indirectos | D10: =ROUND(D9*0.1,0) -> 9108000
A11: Costo Licencias | B11: Software libre – sin costo adicional | C11: 0 | D11: 0
A12: Costo Total Proyecto | B12: RRHH + Indirectos + Caja + Licencias | D12: =D9+D10+D11 -> 100188000
A14: Fuente: Elaborado por el equipo de trabajo de acuerdo con el proyecto.

Sheet A.2 Beneficios
A1: Tabla A.2 — Beneficios estimados del proyecto
A2: Beneficios operacionales esperados tras la implementación del sistema
A4: Fuente de beneficio | B4: Beneficio mensual | C4: Beneficio anual | D4: Supuesto
A5: Ahorro en horas de trabajo manual | B5: 80000 | C5: =B5*12 -> 960000 | D5: ~10 hrs/mes × $8.000/hr
A6: Reducción de errores y pérdidas de stock | B6: 120000 | C6: =B6*12 -> 1440000 | D6: Pérdidas evitadas estimadas
A7: Ahorro en gestión de facturas | B7: 50000 | C7: =B7*12 -> 600000 | D7: Horas administrativas ahorradas
A8: Mejora en ventas por stock disponible | B8: 150000 | C8: =B8*12 -> 1800000 | D8: ~2% incremento en ventas
A9: Reducción de quiebres de stock | B9: 60000 | C9: =B9*12 -> 720000 | D9: Ventas perdidas evitadas
A10: BENEFICIO TOTAL | B10: =SUM(B5:B9) -> 460000 | C10: =SUM(C5:C9) -> 5520000
A12: Fuente: Elaborado por el equipo de trabajo de acuerdo con el proyecto.

Sheet A.3 Flujo de caja
A1: Tabla A.3 — Flujo de caja proyectado a 12 meses
A2: Mes 0: desembolso de caja/contingencia. Meses 1–12: costos operativos de RRHH e indirectos vs. beneficios mensuales.
A4: Período | B4: Ingresos / Beneficios | C4: Egresos / Costos | D4: Flujo neto | E4: Flujo acumulado
A5: Mes 0 | B5: 0 | C5: ='A.1 Costos'!D10 -> 9108000 | D5: =B5-C5 -> -9108000 | E5: =D5 -> -9108000
A6: Mes 1 | B6: ='A.2 Beneficios'!B10 -> 460000 | C6: ='A.1 Costos'!C9 -> 7590000 | D6: =B6-C6 -> -7130000 | E6: =E5+D6 -> -16238000
A7: Mes 2 | B7: ='A.2 Beneficios'!B10 -> 460000 | C7: ='A.1 Costos'!C9 -> 7590000 | D7: =B7-C7 -> -7130000 | E7: =E6+D7 -> -23368000
A8: Mes 3 | B8: ='A.2 Beneficios'!B10 -> 460000 | C8: ='A.1 Costos'!C9 -> 7590000 | D8: =B8-C8 -> -7130000 | E8: =E7+D8 -> -30498000
A9: Mes 4 | B9: ='A.2 Beneficios'!B10 -> 460000 | C9: ='A.1 Costos'!C9 -> 7590000 | D9: =B9-C9 -> -7130000 | E9: =E8+D9 -> -37628000
A10: Mes 5 | B10: ='A.2 Beneficios'!B10 -> 460000 | C10: ='A.1 Costos'!C9 -> 7590000 | D10: =B10-C10 -> -7130000 | E10: =E9+D10 -> -44758000
A11: Mes 6 | B11: ='A.2 Beneficios'!B10 -> 460000 | C11: ='A.1 Costos'!C9 -> 7590000 | D11: =B11-C11 -> -7130000 | E11: =E10+D11 -> -51888000
A12: Mes 7 | B12: ='A.2 Beneficios'!B10 -> 460000 | C12: ='A.1 Costos'!C9 -> 7590000 | D12: =B12-C12 -> -7130000 | E12: =E11+D12 -> -59018000
A13: Mes 8 | B13: ='A.2 Beneficios'!B10 -> 460000 | C13: ='A.1 Costos'!C9 -> 7590000 | D13: =B13-C13 -> -7130000 | E13: =E12+D13 -> -66148000
A14: Mes 9 | B14: ='A.2 Beneficios'!B10 -> 460000 | C14: ='A.1 Costos'!C9 -> 7590000 | D14: =B14-C14 -> -7130000 | E14: =E13+D14 -> -73278000
A15: Mes 10 | B15: ='A.2 Beneficios'!B10 -> 460000 | C15: ='A.1 Costos'!C9 -> 7590000 | D15: =B15-C15 -> -7130000 | E15: =E14+D15 -> -80408000
A16: Mes 11 | B16: ='A.2 Beneficios'!B10 -> 460000 | C16: ='A.1 Costos'!C9 -> 7590000 | D16: =B16-C16 -> -7130000 | E16: =E15+D16 -> -87538000
A17: Mes 12 | B17: ='A.2 Beneficios'!B10 -> 460000 | C17: ='A.1 Costos'!C9 -> 7590000 | D17: =B17-C17 -> -7130000 | E17: =E16+D17 -> -94668000
A18: TOTAL AÑO | B18: =SUM(B5:B17) -> 5520000 | C18: =SUM(C5:C17) -> 100188000 | D18: =SUM(D5:D17) -> -94668000
A20: Nota: el Mes 0 corresponde al desembolso de la caja/contingencia (-$9.108.000). Los meses 1 al 12 incluyen el costo mensual de RRHH e indirectos (-$7.590.000) con beneficios operacionales de $460.000 mensuales.
A22: Fuente: Elaborado por el equipo de trabajo de acuerdo con el proyecto.

Sheet A.4 Indicadores
A1: Tabla A.4 — Indicadores financieros
A2: Indicadores evaluados sobre el período de desarrollo de 12 meses
A4: Indicador | B4: Valor | C4: Interpretación
A5: Inversión total | B5: ='A.1 Costos'!D12 -> 100188000 | C5: Suma de RRHH + Indirectos + Caja + Licencias
A6: Beneficio mensual | B6: ='A.2 Beneficios'!B10 -> 460000 | C6: Ahorro y mejoras operacionales mensuales estimados
A7: Beneficio anual | B7: ='A.2 Beneficios'!C10 -> 5520000 | C7: Beneficio mensual × 12 meses
A8: Ganancia neta anual | B8: =B7-B5 -> -94668000 | C8: Beneficio anual − Inversión total
A9: ROI | B9: -0.055 | C9: Negativo en el primer año; proyecto de valor estratégico y social
A10: VAN | B10: Negativo | C10: Proyecto académico de primer desarrollo; valor social/operacional justifica la inversión
A11: TIR | B11: N/D | C11: No alcanza tasa positiva en el período de desarrollo; se evalúa en fase de operación
A12: Período de recuperación | B12: >12 meses | C12: Se requiere fase de operación para recuperar la inversión
A14: Fuente: Elaborado por el equipo de trabajo de acuerdo con el proyecto.
A16: Notas complementarias
A17: Naturaleza del proyecto: El presente proyecto corresponde al desarrollo inicial de un sistema de información a medida para Minimarket Antucayen, no a la operación continua del software. El flujo de caja del año de desarrollo es estructuralmente negativo y no debe interpretarse como falta de viabilidad, sino como la inversión inicial de cualquier proyecto de software a medida.
A18: Justificación del costo mensual: $7.590.000 = $6.600.000 en remuneraciones (7 integrantes) + 15% de costos indirectos. La caja de contingencia del 10% ($9.108.000) es práctica estándar para cubrir desviaciones. No hay costos de licencias por uso de tecnologías de código abierto.
A19: Análisis de sensibilidad: Escenario conservador: $460.000/mes (supuestos auditables). Escenario optimista con uso intensivo, capacitación efectiva y crecimiento de 4% en ventas: hasta $850.000/mes, reduciendo el período de recuperación a ~24 meses post-entrega.
A20: Horizonte real de evaluación: Considerando una vida útil de 5 años post-entrega y beneficios constantes de $460.000/mes, el flujo acumulado se vuelve positivo entre el año 4 y 5 de operación, generando un VAN positivo en el escenario base y ROI positivo a partir del año 4.
