Workbook

Sheet Sprint Backlog
A1: PILA DEL PRODUCTO — SPRINT BACKLOG — INCREMENTO 3 | Grupo 20 — Minimarket Antucayen | I1: OBJETIVO: Implementar módulos de Exportación/Auditoría de archivos, Reversión de ajustes, Historial/Consulta de stock y Reportes exportables a Excel → 10 URs prioridad 3 | N1: Entrega: 11/10/2026 23:59
A2: Prioridad | B2: Categoría | C2: ID | D2: Descripción detallada | E2: Responsable | F2: HH Est. | G2: Estado | H2: Criterio de aceptación | I2: URs relacionadas | J2: Notas / Dependencias | K2: Herramientas | L2: Fecha límite | M2: Fecha inicio | N2: Fecha término | O2: HH Efectivas | P2: Semana
A3: 3 | B3: Retroalimentación Inc. 2 | C3: 1.1 | D3: Revisar la retroalimentación y observaciones recibidas sobre el Incremento 2 (comentarios del profesor y/o pauta de corrección) y contrastarlas con el Sprint Retrospective del Incremento 2, elaborando un listado priorizado de acciones correctivas para el Incremento 3. | E3: Cristobal Osorio | F3: 2 | G3: Listo | H3: Listado de acciones correctivas con al menos 3 puntos, cada uno con responsable tentativo; referencia explícita a la retroalimentación del profesor o, en su defecto, a la Retrospectiva del Incremento 2. | I3: — | J3: Si la retroalimentación formal del profesor aún no llega, usar como base el Sprint Retrospective del Incremento 2 (documento Incremento 2, sección Scrum++). | K3: Word | L3: 46281 | M3: 46280 | N3: 46281 | O3: 2.5 | P3: 1
A4: 3 | B4: Retroalimentación Inc. 2 | C4: 1.2 | D4: Incorporar las acciones correctivas identificadas en 1.1 a la planificación del Incremento 3 (Product Backlog y este Sprint Backlog) y dejar registro explícito de qué cambió respecto al Incremento 2. | E4: Cristobal Osorio | F4: 1 | G4: Listo | H4: Cada acción correctiva queda vinculada a una tarea o nota del Sprint Backlog del Incremento 3; el documento Word incluye un párrafo "Cambios respecto al Incremento 2". | I4: — | J4: Depende de 1.1. | K4: Word / Excel | L4: 46283 | M4: 46282 | N4: 46282 | O4: 1 | P4: 1
A5: 3 | B5: Modelo | C5: 2.1 | D5: Implementar ServicioExportacion (nuevo): exportarItemsValidos(lista, formato) genera un archivo con las columnas SKU y cantidad a partir de la lista de ítems válidos de una importación o ajuste, en formato Excel (Apache POI) y CSV. | E5: Felipe Salas | F5: 4 | G5: Listo | H5: Exportación a Excel y a CSV generan archivos válidos y abribles; columnas SKU y cantidad correctas; nombre de archivo incluye fecha/hora. | I5: UR-25 | J5: Depende de ServicioImportacion y ServicioAjusteInventario (Incremento 1 y 2). Requiere Apache POI (ya incluido en pom.xml). | K5: IntelliJ IDEA | L5: 46285 | M5: 46281 | N5: 46284 | O5: 5 | P5: 1
A6: 3 | B6: Modelo | C6: 2.2 | D6: Implementar ServicioAuditoria (nuevo) y tabla auditoria_archivo (fecha, hora, usuario, nombre de archivo, tipo de operación): registrarEvento(tipoOperacion, usuario, nombreArchivo). Crear AuditoriaDAO e integrar la llamada en ServicioImportacion y ServicioExportacion. | E6: Nicolas Lopez | F6: 4 | G6: Listo | H6: Cada importación y exportación genera un registro de auditoría persistido; una consulta directa a la tabla confirma fecha/hora/usuario/archivo correctos. | I6: UR-37 | J6: Requiere script SQL para la tabla auditoria_archivo (agregar a los scripts del proyecto). Depende de 2.1 para integrarse con la exportación. | K6: IntelliJ IDEA / MySQL Workbench | L6: 46285 | M6: 46282 | N6: 46285 | O6: 5 | P6: 1
A7: 3 | B7: Modelo | C7: 2.3 | D7: Extender ServicioAjusteInventario: revertirAjuste(idMovimiento) — valida que el usuario tenga rol Administrador, recupera el stock anterior desde MovimientoDAO, restaura el stock del producto y registra un nuevo movimiento tipo "Reversión" referenciando el ajuste revertido. | E7: Fabian Gomez | F7: 4 | G7: Listo | H7: Reversión exitosa deja el stock igual al valor previo al ajuste; usuario sin rol Administrador recibe AccesoNoAutorizadoException; queda un nuevo movimiento tipo Reversión en el historial. | I7: UR-46 | J7: Depende de ServicioAjusteInventario y MovimientoDAO (Incremento 1) y de ServicioUsuario para validar el rol (Incremento 1). | K7: IntelliJ IDEA | L7: 46289 | M7: 46286 | N7: 46288 | O7: 4 | P7: 2
A8: 3 | B8: Modelo | C8: 2.4 | D8: Extender ServicioHistorial: asegurar que consultarMovimientos() retorne tipo, fecha, hora, usuario, SKU, stock anterior y stock resultante en todos los movimientos; agregar obtenerUltimosMovimientos(sku, 10) ordenado por fecha descendente. | E8: Nicolas Lopez | F8: 3 | G8: Listo | H8: La consulta general retorna los 6 campos requeridos sin nulos; obtenerUltimosMovimientos retorna máximo 10 filas y nunca más que los movimientos reales existentes. | I8: UR-47,UR-56 | J8: Depende de ServicioHistorial y MovimientoDAO (Incremento 1). Revisar consistencia con lo ya implementado como UR-47 en el Incremento 1. | K8: IntelliJ IDEA | L8: 46290 | M8: 46288 | N8: 46289 | O8: 2.5 | P8: 2
A9: 3 | B9: Modelo | C9: 2.5 | D9: Implementar ServicioReportes (nuevo): reporteStock() (productos activos con stock actual), reporteEquivalenciasFaltantes() (códigos de proveedor sin SKU asociado), reporteFacturas(estado, fechaInicio, fechaFin), reporteMovimientos(fechaInicio, fechaFin). | E9: Matias Ale | F9: 6 | G9: Listo | H9: Los 4 métodos retornan listas correctas contra datos de prueba conocidos; los filtros de facturas y movimientos combinan estado/rango de fechas correctamente; el reporte de equivalencias solo incluye códigos sin SKU asociado. | I9: UR-57,UR-58,UR-59,UR-60 | J9: Depende de ServicioProducto, ServicioEquivalencia (Incremento 2), ServicioFactura (Incremento 2) y ServicioHistorial. | K9: IntelliJ IDEA | L9: 46291 | M9: 46286 | N9: 46290 | O9: 8 | P9: 2
A10: 3 | B10: Modelo | C10: 2.6 | D10: Integrar ServicioExportacion (2.1) con ServicioReportes (2.5): exportarReporteExcel(tipoReporte, datos) para los 4 reportes de RF-57 a RF-60, reutilizando el motor Apache POI y registrando auditoría de cada exportación mediante ServicioAuditoria (2.2). | E10: Felipe Salas | F10: 3 | G10: Listo | H10: Cada uno de los 4 reportes se exporta a un archivo Excel legible con encabezados correctos; cada exportación genera su registro de auditoría. | I10: UR-61 | J10: Depende de 2.1, 2.2 y 2.5. | K10: IntelliJ IDEA | L10: 46292 | M10: 46291 | N10: 46292 | O10: 4 | P10: 2
A11: 3 | B11: Vista | C11: 3.1 | D11: Extender la vista de ajuste/importación de inventario (VAjusteInventario): agregar botón "Exportar ítems válidos" tras la previsualización, con JFileChooser para elegir formato (Excel/CSV) y carpeta destino. | E11: Felipe Salas | F11: 2 | G11: Listo | H11: Botón visible tras previsualizar un archivo válido; selector de formato funcional; confirmación visual al finalizar la exportación. | I11: UR-25 | J11: Depende de VAjusteInventario (Incremento 1) y de 2.1. | K11: IntelliJ IDEA + WindowBuilder | L11: 46289 | M11: 46287 | N11: 46287 | O11: 1.5 | P11: 2
A12: 3 | B12: Vista | C12: 3.2 | D12: Crear VRevertirAjuste (JDialog) o extender VHistorialMovimientos: botón "Revertir" visible solo para Administrador junto a movimientos de tipo ajuste, con diálogo de confirmación mostrando el detalle del movimiento a revertir. | E12: Diego Lobos | F12: 3 | G12: Listo | H12: Botón oculto/deshabilitado para roles distintos de Administrador; la confirmación muestra SKU, cantidad y fecha del ajuste antes de revertir; mensaje de éxito o error visible. | I12: UR-46 | J12: Depende de VHistorialMovimientos (Incremento 1) y de 2.3. | K12: IntelliJ IDEA + WindowBuilder | L12: 46290 | M12: 46289 | N12: 46290 | O12: 3.5 | P12: 2
A13: 3 | B13: Vista | C13: 3.3 | D13: Crear VConsultaStockHistorial (JPanel): buscador de producto por SKU o nombre, panel con stock actual y JTable con los últimos 10 movimientos (tipo, fecha, hora, usuario, stock anterior, stock resultante). | E13: Nicolas Lopez | F13: 3 | G13: Listo | H13: La búsqueda por SKU o nombre muestra el producto correcto; la JTable muestra máximo 10 filas ordenadas por fecha descendente; el stock actual coincide con ServicioProducto. | I13: UR-47,UR-56 | J13: Depende de VPrincipal y de 2.4. | K13: IntelliJ IDEA + WindowBuilder | L13: 46291 | M13: 46290 | N13: 46291 | O13: 3.5 | P13: 2
A14: 3 | B14: Vista | C14: 3.4 | D14: Crear VReportes (JPanel con JComboBox de tipo de reporte): filtros según el reporte seleccionado (rango de fechas para movimientos y facturas, estado para facturas), JTable de resultados y botón "Exportar a Excel" por reporte. | E14: Felipe Salas | F14: 4 | G14: Listo | H14: El selector cambia los filtros disponibles según el reporte; la JTable se puebla correctamente para los 4 reportes; el botón exportar se habilita solo con resultados en pantalla. | I14: UR-57,UR-58,UR-59,UR-60,UR-61 | J14: Depende de VPrincipal y de 2.5, 2.6. | K14: IntelliJ IDEA + WindowBuilder | L14: 46292 | M14: 46290 | N14: 46292 | O14: 4.5 | P14: 2
... A49: 3 | B49: Documentación | C49: 9.6 | D49: Enviar correo al profesor con el enlace de Drive. Asunto exacto acordado por el equipo. Solo el jefe de proyecto envía. Verificar permisos de visualización del enlace. | E49: Cristobal Osorio | F49: 0.5 | G49: Listo | H49: Correo enviado antes del 11/10 23:59; asunto correcto; enlace funcional. | I49: — | J49: Deadline: domingo 11 de octubre 23:59. | K49: Gmail / Outlook | L49: 46299 | M49: 46298 | N49: 46299 | O49: 0.5 | P49: 4
A51: RESUMEN DE CARGA POR INTEGRANTE
A52: Integrante | B52: N° de tareas | C52: HH estimadas totales
A53: Cristobal Osorio | B53: =COUNTIF($E$3:$E$49,A53) -> 8 | C53: =SUMIF($E$3:$E$49,A53,$F$3:$F$49) -> 14.5
A54: Diego Lobos | B54: =COUNTIF($E$3:$E$49,A54) -> 7 | C54: =SUMIF($E$3:$E$49,A54,$F$3:$F$49) -> 17
A55: Erick Hernandez | B55: =COUNTIF($E$3:$E$49,A55) -> 8 | C55: =SUMIF($E$3:$E$49,A55,$F$3:$F$49) -> 15
A56: Fabian Gomez | B56: =COUNTIF($E$3:$E$49,A56) -> 6 | C56: =SUMIF($E$3:$E$49,A56,$F$3:$F$49) -> 16
A57: Felipe Salas | B57: =COUNTIF($E$3:$E$49,A57) -> 6 | C57: =SUMIF($E$3:$E$49,A57,$F$3:$F$49) -> 18
A58: Matias Ale | B58: =COUNTIF($E$3:$E$49,A58) -> 5 | C58: =SUMIF($E$3:$E$49,A58,$F$3:$F$49) -> 14
A59: Nicolas Lopez | B59: =COUNTIF($E$3:$E$49,A59) -> 7 | C59: =SUMIF($E$3:$E$49,A59,$F$3:$F$49) -> 16
A60: TOTAL | B60: =SUM(B53:B59) -> 47 | C60: =SUM(C53:C59) -> 110.5
A62: DISTRIBUCIÓN SEMANAL DE HH (referencia: máx. 2 HH/persona/día ≈ 14 HH/semana)
A63: Integrante | B63: Semana 1 (14-20 sep) | C63: Semana 2 (21-27 sep) | D63: Semana 3 (28 sep-4 oct) | E63: Semana 4 (5-11 oct) | F63: Total
A64: Cristobal Osorio | B64: =SUMIFS($F$3:$F$49,$E$3:$E$49,A64,$P$3:$P$49,1) -> 4 | C64: =SUMIFS($F$3:$F$49,$E$3:$E$49,A64,$P$3:$P$49,2) -> 0 | D64: =SUMIFS($F$3:$F$49,$E$3:$E$49,A64,$P$3:$P$49,3) -> 0 | E64: =SUMIFS($F$3:$F$49,$E$3:$E$49,A64,$P$3:$P$49,4) -> 10.5 | F64: =SUM(B64:E64) -> 14.5
A65: Diego Lobos | B65: =SUMIFS($F$3:$F$49,$E$3:$E$49,A65,$P$3:$P$49,1) -> 1 | C65: =SUMIFS($F$3:$F$49,$E$3:$E$49,A65,$P$3:$P$49,2) -> 3 | D65: =SUMIFS($F$3:$F$49,$E$3:$E$49,A65,$P$3:$P$49,3) -> 8 | E65: =SUMIFS($F$3:$F$49,$E$3:$E$49,A65,$P$3:$P$49,4) -> 5 | F65: =SUM(B65:E65) -> 17
A66: Erick Hernandez | B66: =SUMIFS($F$3:$F$49,$E$3:$E$49,A66,$P$3:$P$49,1) -> 3 | C66: =SUMIFS($F$3:$F$49,$E$3:$E$49,A66,$P$3:$P$49,2) -> 0 | D66: =SUMIFS($F$3:$F$49,$E$3:$E$49,A66,$P$3:$P$49,3) -> 0 | E66: =SUMIFS($F$3:$F$49,$E$3:$E$49,A66,$P$3:$P$49,4) -> 12 | F66: =SUM(B66:E66) -> 15
A67: Fabian Gomez | B67: =SUMIFS($F$3:$F$49,$E$3:$E$49,A67,$P$3:$P$49,1) -> 0 | C67: =SUMIFS($F$3:$F$49,$E$3:$E$49,A67,$P$3:$P$49,2) -> 4 | D67: =SUMIFS($F$3:$F$49,$E$3:$E$49,A67,$P$3:$P$49,3) -> 9 | E67: =SUMIFS($F$3:$F$49,$E$3:$E$49,A67,$P$3:$P$49,4) -> 3 | F67: =SUM(B67:E67) -> 16
A68: Felipe Salas | B68: =SUMIFS($F$3:$F$49,$E$3:$E$49,A68,$P$3:$P$49,1) -> 4 | C68: =SUMIFS($F$3:$F$49,$E$3:$E$49,A68,$P$3:$P$49,2) -> 9 | D68: =SUMIFS($F$3:$F$49,$E$3:$E$49,A68,$P$3:$P$49,3) -> 5 | E68: =SUMIFS($F$3:$F$49,$E$3:$E$49,A68,$P$3:$P$49,4) -> 0 | F68: =SUM(B68:E68) -> 18
A69: Matias Ale | B69: =SUMIFS($F$3:$F$49,$E$3:$E$49,A69,$P$3:$P$49,1) -> 0 | C69: =SUMIFS($F$3:$F$49,$E$3:$E$49,A69,$P$3:$P$49,2) -> 6 | D69: =SUMIFS($F$3:$F$49,$E$3:$E$49,A69,$P$3:$P$49,3) -> 4 | E69: =SUMIFS($F$3:$F$49,$E$3:$E$49,A69,$P$3:$P$49,4) -> 4 | F69: =SUM(B69:E69) -> 14
A70: Nicolas Lopez | B70: =SUMIFS($F$3:$F$49,$E$3:$E$49,A70,$P$3:$P$49,1) -> 4 | C70: =SUMIFS($F$3:$F$49,$E$3:$E$49,A70,$P$3:$P$49,2) -> 7 | D70: =SUMIFS($F$3:$F$49,$E$3:$E$49,A70,$P$3:$P$49,3) -> 2 | E70: =SUMIFS($F$3:$F$49,$E$3:$E$49,A70,$P$3:$P$49,4) -> 3 | F70: =SUM(B70:E70) -> 16
A71: TOTAL | B71: =SUM(B64:B70) -> 16 | C71: =SUM(C64:C70) -> 29 | D71: =SUM(D64:D70) -> 28 | E71: =SUM(E64:E70) -> 37.5 | F71: =SUM(F64:F70) -> 110.5

Sheet URs Prioridad 3 (Referencia)
A1: REQUERIMIENTOS (URs) DE PRIORIDAD 3 — INCREMENTO 3 | Grupo 20 — Minimarket Antucayen
A2: ID UR | B2: Nombre | C2: Descripción | D2: Módulo relacionado (Sprint Backlog)
A3: UR-25 | B3: Exportando lista de ítems válidos | C3: Generar una lista de ítems válidos con SKU y cantidad, exportable en Excel y CSV. | D3: Modelo 2.1 / Vista 3.1 / Controlador 4.1
A4: UR-37 | B4: Registrando auditoría de archivo | C4: Registrar fecha, hora, usuario y nombre del archivo en cada importación/exportación. | D4: Modelo 2.2
A5: UR-46 | B5: Revirtiendo ajuste | C5: Permitir revertir un ajuste confirmado y restaurar el stock anterior; exclusivo de Administrador. | D5: Modelo 2.3 / Vista 3.2 / Controlador 4.2
A6: UR-47 | B6: Consultando historial de movimientos | C6: Mantener un historial consultable con tipo, fecha, hora, usuario, SKU, stock anterior y resultante. | D6: Modelo 2.4 / Vista 3.3 / Controlador 4.3
A7: UR-56 | B7: Consultando stock e historial | C7: Mostrar stock actual junto con los últimos 10 movimientos del producto. | D7: Modelo 2.4 / Vista 3.3 / Controlador 4.3
A8: UR-57 | B8: Generando reporte de stock | C8: Generar reporte del stock actual de todos los productos activos, exportable a Excel. | D8: Modelo 2.5 / Vista 3.4 / Controlador 4.4
A9: UR-58 | B9: Reportando equivalencias faltantes | C9: Generar reporte de productos con códigos de proveedor sin equivalencia SKU. | D9: Modelo 2.5 / Vista 3.4 / Controlador 4.4
A10: UR-59 | B10: Generando reporte de facturas | C10: Generar reporte de facturas filtrable por estado y rango de fechas. | D10: Modelo 2.5 / Vista 3.4 / Controlador 4.4
A11: UR-60 | B11: Generando reporte de movimientos | C11: Generar reporte de movimientos de inventario filtrable por rango de fechas. | D11: Modelo 2.5 / Vista 3.4 / Controlador 4.4
A12: UR-61 | B12: Exportando reportes a Excel | C12: Permitir exportar a Excel los reportes de RF-57, RF-58, RF-59 y RF-60. | D12: Modelo 2.6 / Vista 3.4 / Controlador 4.4

Sheet Trazabilidad Incremento 3
A1: TRAZABILIDAD DEL DOCUMENTO — INCREMENTO 3 | Grupo 20 — Minimarket Antucayen
A2: Incremento 3 | B2: Responsables (redacción) | C2: Verificadores (revisión) | D2: Estatus
A3: Retroalimentación Incremento 2 y acciones correctivas | D3: Pendiente
A4: Aspectos formales del documento (portada, índices, redacción, formato) | D4: Pendiente
A5: Introducción | B5: Erick | D5: Listo
A6: Propuesta de Solución e Incremento 3 (RFs/URs, % parcial y acumulado) | D6: Pendiente
A7: Resumen acumulado de Incrementos 1 y 2 | D7: Pendiente
A8: Documentación Scrum++: Product Backlog actualizado | D8: Pendiente
A9: Documentación Scrum++: Sprint Backlog y tabla de esfuerzo | D9: Pendiente
A10: Documentación Scrum++: Actas de Daily Scrum | D10: Pendiente
A11: Documentación Scrum++: Sprint Review | D11: Pendiente
A12: Documentación Scrum++: Sprint Retrospective | D12: Pendiente
A13: Vista Lógica (diagrama de clases actualizado) | D13: Pendiente
A14: Vista de Procesos (diagramas de secuencia — 4 módulos) | D14: Pendiente
A15: Vista de Desarrollo y Vista Física (verificación sin cambios estructurales) | D15: Pendiente
A16: Vista Externa (casos de uso extendidos, nombre en gerundio) | D16: Pendiente
A17: Árbol de navegación actualizado | D17: Pendiente
... A27: Historial de commits Git de todos los integrantes | D27: Pendiente

Sheet Burn Down - Burn Up
A1: BURN DOWN / BURN UP — INCREMENTO 3 | Grupo 20 — Minimarket Antucayen
A3: Inicio sprint | B3: 46279 | D3: Nota: una tarea se considera completada en su "Fecha término" (col. N del Sprint Backlog). Las fechas de inicio/fin del sprint (azul) son editables.
A4: Fin sprint | B4: 46299
A5: Alcance total (HH Est.) | B5: =SUM('Sprint Backlog'!F3:F49) -> 110.5
A6: HH Efectivas totales | B6: =SUM('Sprint Backlog'!O3:O49) -> 127
A7: Días del sprint | B7: =B4-B3 -> 20
A9: Día | B9: Fecha | C9: Ideal restante (HH) | D9: Real restante (HH) | E9: Alcance total (HH) | F9: Ideal completado (HH) | G9: Real completado (HH) | H9: HH Efectivas acumuladas
A10: 0 | B10: =$B$3+A10 -> 46279 | C10: =MAX(0,$B$5-$B$5*A10/$B$7) -> 110.5 | D10: =$B$5-SUMIFS('Sprint Backlog'!$F$3:$F$49,'Sprint Backlog'!$N$3:$N$49,"<="&B10) -> 109.5 | E10: =$B$5 -> 110.5 | F10: =$B$5-C10 -> 0 | G10: =$B$5-D10 -> 1 | H10: =SUMIFS('Sprint Backlog'!$O$3:$O$49,'Sprint Backlog'!$N$3:$N$49,"<="&B10) -> 1
A11: 1 | B11: =$B$3+A11 -> 46280 | C11: =MAX(0,$B$5-$B$5*A11/$B$7) -> 104.975 | D11: =$B$5-SUMIFS('Sprint Backlog'!$F$3:$F$49,'Sprint Backlog'!$N$3:$N$49,"<="&B11) -> 108.5 | E11: =$B$5 -> 110.5 | F11: =$B$5-C11 -> 5.525 | G11: =$B$5-D11 -> 2 | H11: =SUMIFS('Sprint Backlog'!$O$3:$O$49,'Sprint Backlog'!$N$3:$N$49,"<="&B11) -> 2
A12: 2 | B12: =$B$3+A12 -> 46281 | C12: =MAX(0,$B$5-$B$5*A12/$B$7) -> 99.45 | D12: =$B$5-SUMIFS('Sprint Backlog'!$F$3:$F$49,'Sprint Backlog'!$N$3:$N$49,"<="&B12) -> 103.5 | E12: =$B$5 -> 110.5 | F12: =$B$5-C12 -> 11.05 | G12: =$B$5-D12 -> 7 | H12: =SUMIFS('Sprint Backlog'!$O$3:$O$49,'Sprint Backlog'!$N$3:$N$49,"<="&B12) -> 8
A13: 3 | B13: =$B$3+A13 -> 46282 | C13: =MAX(0,$B$5-$B$5*A13/$B$7) -> 93.925 | D13: =$B$5-SUMIFS('Sprint Backlog'!$F$3:$F$49,'Sprint Backlog'!$N$3:$N$49,"<="&B13) -> 102.5 | E13: =$B$5 -> 110.5 | F13: =$B$5-C13 -> 16.575 | G13: =$B$5-D13 -> 8 | H13: =SUMIFS('Sprint Backlog'!$O$3:$O$49,'Sprint Backlog'!$N$3:$N$49,"<="&B13) -> 9
A14: 4 | B14: =$B$3+A14 -> 46283 | C14: =MAX(0,$B$5-$B$5*A14/$B$7) -> 88.4 | D14: =$B$5-SUMIFS('Sprint Backlog'!$F$3:$F$49,'Sprint Backlog'!$N$3:$N$49,"<="&B14) -> 101.5 | E14: =$B$5 -> 110.5 | F14: =$B$5-C14 -> 22.1 | G14: =$B$5-D14 -> 9 | H14: =SUMIFS('Sprint Backlog'!$O$3:$O$49,'Sprint Backlog'!$N$3:$N$49,"<="&B14) -> 10
A15: 5 | B15: =$B$3+A15 -> 46284 | C15: =MAX(0,$B$5-$B$5*A15/$B$7) -> 82.875 | D15: =$B$5-SUMIFS('Sprint Backlog'!$F$3:$F$49,'Sprint Backlog'!$N$3:$N$49,"<="&B15) -> 97.5 | E15: =$B$5 -> 110.5 | F15: =$B$5-C15 -> 27.625 | G15: =$B$5-D15 -> 13 | H15: =SUMIFS('Sprint Backlog'!$O$3:$O$49,'Sprint Backlog'!$N$3:$N$49,"<="&B15) -> 15
A16: 6 | B16: =$B$3+A16 -> 46285 | C16: =MAX(0,$B$5-$B$5*A16/$B$7) -> 77.35 | D16: =$B$5-SUMIFS('Sprint Backlog'!$F$3:$F$49,'Sprint Backlog'!$N$3:$N$49,"<="&B16) -> 93.5 | E16: =$B$5 -> 110.5 | F16: =$B$5-C16 -> 33.15 | G16: =$B$5-D16 -> 17 | H16: =SUMIFS('Sprint Backlog'!$O$3:$O$49,'Sprint Backlog'!$N$3:$N$49,"<="&B16) -> 20
A17: 7 | B17: =$B$3+A17 -> 46286 | C17: =MAX(0,$B$5-$B$5*A17/$B$7) -> 71.825 | D17: =$B$5-SUMIFS('Sprint Backlog'!$F$3:$F$49,'Sprint Backlog'!$N$3:$N$49,"<="&B17) -> 93.5 | E17: =$B$5 -> 110.5 | F17: =$B$5-C17 -> 38.675 | G17: =$B$5-D17 -> 17 | H17: =SUMIFS('Sprint Backlog'!$O$3:$O$49,'Sprint Backlog'!$N$3:$N$49,"<="&B17) -> 20
A18: 8 | B18: =$B$3+A18 -> 46287 | C18: =MAX(0,$B$5-$B$5*A18/$B$7) -> 66.3 | D18: =$B$5-SUMIFS('Sprint Backlog'!$F$3:$F$49,'Sprint Backlog'!$N$3:$N$49,"<="&B18) -> 91.5 | E18: =$B$5 -> 110.5 | F18: =$B$5-C18 -> 44.2 | G18: =$B$5-D18 -> 19 | H18: =SUMIFS('Sprint Backlog'!$O$3:$O$49,'Sprint Backlog'!$N$3:$N$49,"<="&B18) -> 21.5
A19: 9 | B19: =$B$3+A19 -> 46288 | C19: =MAX(0,$B$5-$B$5*A19/$B$7) -> 60.775 | D19: =$B$5-SUMIFS('Sprint Backlog'!$F$3:$F$49,'Sprint Backlog'!$N$3:$N$49,"<="&B19) -> 87.5 | E19: =$B$5 -> 110.5 | F19: =$B$5-C19 -> 49.725 | G19: =$B$5-D19 -> 23 | H19: =SUMIFS('Sprint Backlog'!$O$3:$O$49,'Sprint Backlog'!$N$3:$N$49,"<="&B19) -> 25.5
A20: 10 | B20: =$B$3+A20 -> 46289 | C20: =MAX(0,$B$5-$B$5*A20/$B$7) -> 55.25 | D20: =$B$5-SUMIFS('Sprint Backlog'!$F$3:$F$49,'Sprint Backlog'!$N$3:$N$49,"<="&B20) -> 84.5 | E20: =$B$5 -> 110.5 | F20: =$B$5-C20 -> 55.25 | G20: =$B$5-D20 -> 26 | H20: =SUMIFS('Sprint Backlog'!$O$3:$O$49,'Sprint Backlog'!$N$3:$N$49,"<="&B20) -> 28
A21: 11 | B21: =$B$3+A21 -> 46290 | C21: =MAX(0,$B$5-$B$5*A21/$B$7) -> 49.725 | D21: =$B$5-SUMIFS('Sprint Backlog'!$F$3:$F$49,'Sprint Backlog'!$N$3:$N$49,"<="&B21) -> 75.5 | E21: =$B$5 -> 110.5 | F21: =$B$5-C21 -> 60.775 | G21: =$B$5-D21 -> 35 | H21: =SUMIFS('Sprint Backlog'!$O$3:$O$49,'Sprint Backlog'!$N$3:$N$49,"<="&B21) -> 39.5
... A30: 20 | B30: =$B$3+A30 -> 46299 | C30: =MAX(0,$B$5-$B$5*A30/$B$7) -> 0 | D30: =$B$5-SUMIFS('Sprint Backlog'!$F$3:$F$49,'Sprint Backlog'!$N$3:$N$49,"<="&B30) -> 0 | E30: =$B$5 -> 110.5 | F30: =$B$5-C30 -> 110.5 | G30: =$B$5-D30 -> 110.5 | H30: =SUMIFS('Sprint Backlog'!$O$3:$O$49,'Sprint Backlog'!$N$3:$N$49,"<="&B30) -> 127
