Workbook

Sheet Sprint Backlog
A1: PILA DEL PRODUCTO — SPRINT BACKLOG — INCREMENTO 1 | Grupo 20 — Minimarket Antucayen | H1: OBJETIVO: Implementar CU-01, CU-04, CU-05 → 24 URs prioridad 1 (34% del backlog) | M1: Entrega: 14/06/2026 23:59
A2: Prioridad | B2: Categoría | C2: ID | D2: Descripción detallada | E2: Responsable | F2: HH Est. | G2: Estado | H2: Criterio de aceptación | I2: URs relacionadas | J2: Notas / Dependencias | K2: Herramientas | L2: Fecha límite | M2: Fecha inicio | N2: Fecha término | O2: HH Efectivas
A3: 1 | B3: Corrección Doc0 | C3: 1.1 | D3: Corregir formato: cada capítulo debe comenzar en hoja nueva. Aplicar salto de página antes de cada título de nivel 1 en todo el documento. | E3: Cristobal Osorio | F3: 1 | G3: Terminado | H3: Documento Word con salto de página antes de cada capítulo; sin capítulos continuando en la misma página. | I3: — | J3: Error 1 del profesor. | K3: Word | L3: 46180 | M3: 46142 | N3: 46142 | O3: 1
A4: 1 | B4: Corrección Doc0 | C4: 1.2 | D4: Corregir BPMN en Bizagi: eliminar numeración de procesos en el lienzo (solo se numeran compuertas), reemplazar líneas segmentadas por líneas de secuencia correctas y agregar objetos de datos faltantes en cada tarea. | E4: Erick Hernández | F4: 3 | G4: Terminado | H4: Diagrama BPMN exportado (.bpmn + PNG) sin números en procesos simples, flujos de secuencia correctos y objetos de datos en cada actividad. | I4: — | J4: Error 2 (grave). Requiere Bizagi Modeler. | K4: Bizagi Modeler | L4: 46180 | M4: 46143 | N4: 46143 | O4: 4
A5: 1 | B5: Corrección Doc0 | C5: 1.3 | D5: Completar análisis del Ishikawa: agregar explicación textual de 3–5 líneas por cada rama (Método, Mano de obra, Materiales, Máquina, Medio ambiente) y párrafo de conclusión después de la figura. | E5: Erick Hernández | F5: 2 | G5: Terminado | H5: Texto explicativo antes y después de la figura; conclusión de mínimo un párrafo luego del Ishikawa. | I5: — | J5: Error 3 del profesor. | K5: Word | L5: 46180 | M5: 46143 | N5: 46143 | O5: 2.5
A6: 1 | B6: Corrección Doc0 | C6: 1.4 | D6: Reclasificar RF-26 (lectura de archivo PDF/JPG/PNG máx 10 MB) a Requerimientos No Funcionales. Verificar todos los RF en busca de otros mal clasificados. | E6: Cristobal Osorio | F6: 1 | G6: Terminado | H6: RF-26 aparece en tabla RNF; tabla RF sin él; sin otros RF mal clasificados. | I6: — | J6: Error 5 del profesor. | K6: Word | L6: 46180 | M6: 46144 | N6: 46144 | O6: 1.5
A7: 1 | B7: Corrección Doc0 | C7: 1.5 | D7: Agregar párrafo introductorio en cap. 8 explicando tecnicismos y abreviaturas (SKU, BPMN, MVC, etc.). Agregar en Anexo vistas/pantallas del sistema con descripción de 2–3 líneas por pantalla. | E7: Erick Hernández | F7: 2 | G7: Terminado | H7: Párrafo introductorio en cap. 8 antes de tabla RF; Anexo de vistas con captura y texto descriptivo por pantalla. | I7: — | J7: Error 4 (grave). | K7: Word | L7: 46180 | M7: 46145 | N7: 46145 | O7: 2.5
A8: 1 | B8: Corrección Doc0 | C8: 1.6 | D8: Corregir leyenda del diagrama de casos de uso (actualmente ilegible). Regenerar diagrama CU con fondo blanco y notación UML correcta. Redactar leyenda clara que explique cada símbolo. | E8: Erick Hernández | F8: 3 | G8: Terminado | H8: Diagrama CU con fondo blanco, notación UML estándar y leyenda comprensible adjunta. | I8: — | J8: Errores 6, 8 y 9 (grave). | K8: draw.io / StarUML | L8: 46180 | M8: 46145 | N8: 46145 | O8: 4
A9: 1 | B9: Corrección Doc0 | C9: 1.7 | D9: Completar columna Prioridad en tabla ESA: revisar que ningún UR quede sin prioridad asignada, especialmente los de Incremento 4. | E9: Cristobal Osorio | F9: 1 | G9: Terminado | H9: Tabla ESA con columna Prioridad completa para todos los URs; ninguna celda vacía. | I9: — | J9: Error 7 del profesor. | K9: Word | L9: 46180 | M9: 46146 | N9: 46146 | O9: 1.5
A10: 1 | B10: Corrección Doc0 | C10: 1.8 | D10: Completar los 14 objetivos específicos indicados en clases. Agregar los que falten con redacción técnica en infinitivo alineada al proyecto. | E10: Cristobal Osorio | F10: 2 | G10: Terminado | H10: Sección de objetivos específicos con exactamente 14 ítems numerados. | I10: — | J10: Error 10 del profesor. | K10: Word | L10: 46180 | M10: 46146 | N10: 46146 | O10: 2.5
A11: 1 | B11: Corrección Doc0 | C11: 1.9 | D11: Estandarizar los 7 CVs: mismo formato, foto formal, mismas secciones (datos personales, perfil, educación, habilidades). Reemplazar CVs que no cumplen el estándar. | E11: Erick Hernández | F11: 2 | G11: Terminado | H11: 7 CVs con formato idéntico, foto formal en cada uno y secciones uniformes. | I11: — | J11: Error 11 del profesor. | K11: Word / Canva | L11: 46180 | M11: 46147 | N11: 46147 | O11: 2.5
A12: 1 | B12: Corrección Doc0 | C12: 1.10 | D12: Corregir Dimensión Técnica en Anexo: eliminar referencias a 'frontend'/'backend', especificar arquitectura MVC real con Vista (Java Swing), Controlador (Java), Modelo (Java + MySQL). Incluir versiones de herramientas. | E12: Cristobal Osorio | F12: 2 | G12: Terminado | H12: Dimensión técnica sin frontend/backend; secciones Vista/Controlador/Modelo con stack y versiones. | I12: — | J12: Error 12 (grave). | K12: Word | L12: 46180 | M12: 46148 | N12: 46148 | O12: 2.5
A13: 1 | B13: Corrección Doc0 | C13: 1.11 | D13: Corregir numeración de figuras y tablas al formato Capítulo.Correlativo (ej: Figura 3.2). Verificar que cada figura y tabla sea invocada y explicada en el texto anterior. | E13: Erick Hernández | F13: 2 | G13: Terminado | H13: Todas las figuras y tablas con numeración correcta; cada una referenciada en el texto. | I13: — | J13: Requisito de rúbrica. | K13: Word | L13: 46180 | M13: 46148 | N13: 46148 | O13: 2.5
A14: 1 | B14: Corrección Doc0 | C14: 1.12 | D14: Agregar citas APA (última versión) en análisis estratégico (PEST, Porter, FODA) e introducción. Completar sección Referencias Bibliográficas al final del documento. | E14: Cristobal Osorio | F14: 2 | G14: Terminado | H14: Referencias en texto con formato APA vigente; sección Referencias Bibliográficas completa al final. | I14: — | J14: Requisito de rúbrica. | K14: Word | L14: 46180 | M14: 46149 | N14: 46149 | O14: 2.5
... A174: 3 | B174: Documentación | C174: 9.6 | D174: Enviar correo al profesor con el enlace de Drive. Asunto exacto acordado por el equipo. Solo el jefe de proyecto envía. Verificar permisos de visualización del enlace. | E174: Cristobal Osorio | F174: 0.5 | G174: Listo | H174: Correo enviado antes del 11/10 23:59; asunto correcto; enlace funcional. | I174: — | J174: Deadline: domingo 11 de octubre 23:59. | K174: Gmail / Outlook | L174: 46299 | M174: 46298 | N174: 46299 | O174: 0.5

Sheet Burn Acumulado
A1: BURN DOWN / BURN UP ACUMULADO — INCREMENTOS 1, 2 Y 3 | Grupo 20 — Minimarket Antucayen
A3: Alcance total (HH Est.) | B3: =SUM('Sprint Backlog'!$F$3:$F$174) -> 404.5 | D3: Periodos: Inc. 1 (30/04–14/06), Inc. 2 (25/08–13/09), Inc. 3 (14/09–11/10). Se omite el receso entre Inc. 1 e Inc. 2. Una tarea se considera completada en su "Fecha término" (col. N del Sprint Backlog).
A4: HH Efectivas totales | B4: =SUM('Sprint Backlog'!$O$3:$O$174) -> 517
A5: Días de sprint considerados | B5: =COUNT(C10:C96) -> 87
A9: Incremento | B9: Día | C9: Fecha | D9: Ideal restante (HH) | E9: Real restante (HH) | F9: Alcance total (HH) | G9: Ideal completado (HH) | H9: Real completado (HH) | I9: HH Efectivas acumuladas
A10: Inc. 1 | B10: 0 | C10: 46142 | D10: =MAX(0,$B$3-$B$3*B10/($B$5-1)) -> 404.5 | E10: =$B$3-SUMIFS('Sprint Backlog'!$F$3:$F$174,'Sprint Backlog'!$N$3:$N$174,"<="&C10) -> 403.5 | F10: =$B$3 -> 404.5 | G10: =$B$3-D10 -> 0 | H10: =$B$3-E10 -> 1 | I10: =SUMIFS('Sprint Backlog'!$O$3:$O$174,'Sprint Backlog'!$N$3:$N$174,"<="&C10) -> 1
A11: Inc. 1 | B11: 1 | C11: 46143 | D11: =MAX(0,$B$3-$B$3*B11/($B$5-1)) -> 399.79651 | E11: =$B$3-SUMIFS('Sprint Backlog'!$F$3:$F$174,'Sprint Backlog'!$N$3:$N$174,"<="&C11) -> 398.5 | F11: =$B$3 -> 404.5 | G11: =$B$3-D11 -> 4.7034884 | H11: =$B$3-E11 -> 6 | I11: =SUMIFS('Sprint Backlog'!$O$3:$O$174,'Sprint Backlog'!$N$3:$N$174,"<="&C11) -> 7.5
A12: Inc. 1 | B12: 2 | C12: 46144 | D12: =MAX(0,$B$3-$B$3*B12/($B$5-1)) -> 395.09302 | E12: =$B$3-SUMIFS('Sprint Backlog'!$F$3:$F$174,'Sprint Backlog'!$N$3:$N$174,"<="&C12) -> 397.5 | F12: =$B$3 -> 404.5 | G12: =$B$3-D12 -> 9.4069767 | H12: =$B$3-E12 -> 7 | I12: =SUMIFS('Sprint Backlog'!$O$3:$O$174,'Sprint Backlog'!$N$3:$N$174,"<="&C12) -> 9
A13: Inc. 1 | B13: 3 | C13: 46145 | D13: =MAX(0,$B$3-$B$3*B13/($B$5-1)) -> 390.38953 | E13: =$B$3-SUMIFS('Sprint Backlog'!$F$3:$F$174,'Sprint Backlog'!$N$3:$N$174,"<="&C13) -> 392.5 | F13: =$B$3 -> 404.5 | G13: =$B$3-D13 -> 14.110465 | H13: =$B$3-E13 -> 12 | I13: =SUMIFS('Sprint Backlog'!$O$3:$O$174,'Sprint Backlog'!$N$3:$N$174,"<="&C13) -> 15.5
A14: Inc. 1 | B14: 4 | C14: 46146 | D14: =MAX(0,$B$3-$B$3*B14/($B$5-1)) -> 385.68605 | E14: =$B$3-SUMIFS('Sprint Backlog'!$F$3:$F$174,'Sprint Backlog'!$N$3:$N$174,"<="&C14) -> 389.5 | F14: =$B$3 -> 404.5 | G14: =$B$3-D14 -> 18.813953 | H14: =$B$3-E14 -> 15 | I14: =SUMIFS('Sprint Backlog'!$O$3:$O$174,'Sprint Backlog'!$N$3:$N$174,"<="&C14) -> 19.5
A15: Inc. 1 | B15: 5 | C15: 46147 | D15: =MAX(0,$B$3-$B$3*B15/($B$5-1)) -> 380.98256 | E15: =$B$3-SUMIFS('Sprint Backlog'!$F$3:$F$174,'Sprint Backlog'!$N$3:$N$174,"<="&C15) -> 384.5 | F15: =$B$3 -> 404.5 | G15: =$B$3-D15 -> 23.517442 | H15: =$B$3-E15 -> 20 | I15: =SUMIFS('Sprint Backlog'!$O$3:$O$174,'Sprint Backlog'!$N$3:$N$174,"<="&C15) -> 26
A16: Inc. 1 | B16: 6 | C16: 46148 | D16: =MAX(0,$B$3-$B$3*B16/($B$5-1)) -> 376.27907 | E16: =$B$3-SUMIFS('Sprint Backlog'!$F$3:$F$174,'Sprint Backlog'!$N$3:$N$174,"<="&C16) -> 380.5 | F16: =$B$3 -> 404.5 | G16: =$B$3-D16 -> 28.22093 | H16: =$B$3-E16 -> 24 | I16: =SUMIFS('Sprint Backlog'!$O$3:$O$174,'Sprint Backlog'!$N$3:$N$174,"<="&C16) -> 31
A17: Inc. 1 | B17: 7 | C17: 46149 | D17: =MAX(0,$B$3-$B$3*B17/($B$5-1)) -> 371.57558 | E17: =$B$3-SUMIFS('Sprint Backlog'!$F$3:$F$174,'Sprint Backlog'!$N$3:$N$174,"<="&C17) -> 375.5 | F17: =$B$3 -> 404.5 | G17: =$B$3-D17 -> 32.924419 | H17: =$B$3-E17 -> 29 | I17: =SUMIFS('Sprint Backlog'!$O$3:$O$174,'Sprint Backlog'!$N$3:$N$174,"<="&C17) -> 37.5
A18: Inc. 1 | B18: 8 | C18: 46150 | D18: =MAX(0,$B$3-$B$3*B18/($B$5-1)) -> 366.87209 | E18: =$B$3-SUMIFS('Sprint Backlog'!$F$3:$F$174,'Sprint Backlog'!$N$3:$N$174,"<="&C18) -> 370.5 | F18: =$B$3 -> 404.5 | G18: =$B$3-D18 -> 37.627907 | H18: =$B$3-E18 -> 34 | I18: =SUMIFS('Sprint Backlog'!$O$3:$O$174,'Sprint Backlog'!$N$3:$N$174,"<="&C18) -> 44
A19: Inc. 1 | B19: 9 | C19: 46151 | D19: =MAX(0,$B$3-$B$3*B19/($B$5-1)) -> 362.1686 | E19: =$B$3-SUMIFS('Sprint Backlog'!$F$3:$F$174,'Sprint Backlog'!$N$3:$N$174,"<="&C19) -> 368.5 | F19: =$B$3 -> 404.5 | G19: =$B$3-D19 -> 42.331395 | H19: =$B$3-E19 -> 36 | I19: =SUMIFS('Sprint Backlog'!$O$3:$O$174,'Sprint Backlog'!$N$3:$N$174,"<="&C19) -> 46.5
A20: Inc. 1 | B20: 10 | C20: 46152 | D20: =MAX(0,$B$3-$B$3*B20/($B$5-1)) -> 357.46512 | E20: =$B$3-SUMIFS('Sprint Backlog'!$F$3:$F$174,'Sprint Backlog'!$N$3:$N$174,"<="&C20) -> 368.5 | F20: =$B$3 -> 404.5 | G20: =$B$3-D20 -> 47.034884 | H20: =$B$3-E20 -> 36 | I20: =SUMIFS('Sprint Backlog'!$O$3:$O$174,'Sprint Backlog'!$N$3:$N$174,"<="&C20) -> 46.5
A21: Inc. 1 | B21: 11 | C21: 46153 | D21: =MAX(0,$B$3-$B$3*B21/($B$5-1)) -> 352.76163 | E21: =$B$3-SUMIFS('Sprint Backlog'!$F$3:$F$174,'Sprint Backlog'!$N$3:$N$174,"<="&C21) -> 362.5 | F21: =$B$3 -> 404.5 | G21: =$B$3-D21 -> 51.738372 | H21: =$B$3-E21 -> 42 | I21: =SUMIFS('Sprint Backlog'!$O$3:$O$174,'Sprint Backlog'!$N$3:$N$174,"<="&C21) -> 54
... A96: Inc. 3 | B96: 86 | C96: 46299 | D96: =MAX(0,$B$3-$B$3*B96/($B$5-1)) -> 0 | E96: =$B$3-SUMIFS('Sprint Backlog'!$F$3:$F$174,'Sprint Backlog'!$N$3:$N$174,"<="&C96) -> 0 | F96: =$B$3 -> 404.5 | G96: =$B$3-D96 -> 404.5 | H96: =$B$3-E96 -> 404.5 | I96: =SUMIFS('Sprint Backlog'!$O$3:$O$174,'Sprint Backlog'!$N$3:$N$174,"<="&C96) -> 517
